{
  "asset": "^DJI",
  "strategy": "HMA_Cross",
  "timestamp": "2026-03-05T22:24:19.363725",
  "best_params": {
    "fast_period": 5,
    "slow_period": 20
  },
  "best_metric": "sharpe",
  "best_value": 0.23485260374667116,
  "total_combinations": 9,
  "valid_combinations": 9,
  "results_summary": {
    "best_sharpe": 0.23485260374667116,
    "best_profit_factor": 1.638038413976156,
    "best_win_rate": 0.46153846153846156,
    "best_return": 4.257198151823679,
    "avg_sharpe": 0.06593503413955429
  }
}