{
  "asset": "^GSPC",
  "strategy": "RSI",
  "timestamp": "2026-03-05T23:53:22.473481",
  "best_params": {
    "oversold": 30,
    "overbought": 80,
    "period": 7
  },
  "best_metric": "sharpe",
  "best_value": -0.14505357644353647,
  "total_combinations": 48,
  "valid_combinations": 48,
  "results_summary": {
    "best_sharpe": -0.14505357644353647,
    "best_profit_factor": 0.7179537411679067,
    "best_win_rate": 0.35714285714285715,
    "best_return": -2.590780440319312,
    "avg_sharpe": -0.5479696751167452
  }
}