{
  "asset": "ADA-USD",
  "strategy": "Keltner",
  "timestamp": "2026-03-05T23:01:08.203561",
  "best_params": {
    "ema_period": 20,
    "atr_period": 20,
    "atr_multiplier": 1.5
  },
  "best_metric": "sharpe",
  "best_value": 0.744191395438477,
  "total_combinations": 18,
  "valid_combinations": 16,
  "results_summary": {
    "best_sharpe": 0.744191395438477,
    "best_profit_factor": 15.896631984347183,
    "best_win_rate": 0.75,
    "best_return": 886.4224240096835,
    "avg_sharpe": 0.5370817250601128
  }
}