{
  "asset": "BTC-USD",
  "strategy": "Awesome",
  "timestamp": "2026-03-05T23:48:28.407549",
  "best_params": {
    "fast_period": 5,
    "slow_period": 34,
    "signal_period": 3
  },
  "best_metric": "sharpe",
  "best_value": 0.0812206642993616,
  "total_combinations": 3,
  "valid_combinations": 3,
  "results_summary": {
    "best_sharpe": 0.0812206642993616,
    "best_profit_factor": 1.2187926843269772,
    "best_win_rate": 0.2857142857142857,
    "best_return": 2.20834311082698,
    "avg_sharpe": 0.0812206642993616
  }
}