{
  "asset": "BTC-USD",
  "strategy": "MACD",
  "timestamp": "2026-03-05T22:13:32.505251",
  "best_params": {
    "fast": 8,
    "slow": 20,
    "signal": 7
  },
  "best_metric": "sharpe",
  "best_value": 0.31467159282368207,
  "total_combinations": 27,
  "valid_combinations": 27,
  "results_summary": {
    "best_sharpe": 0.31467159282368207,
    "best_profit_factor": 2.0338757732987425,
    "best_win_rate": 0.4482758620689655,
    "best_return": 13.124588672569763,
    "avg_sharpe": 0.15952622867426158
  }
}