{
  "asset": "MSFT",
  "strategy": "CCI",
  "timestamp": "2026-03-05T23:44:14.300053",
  "best_params": {
    "period": 10,
    "oversold": -100,
    "overbought": 200
  },
  "best_metric": "sharpe",
  "best_value": -0.25400700800304515,
  "total_combinations": 36,
  "valid_combinations": 36,
  "results_summary": {
    "best_sharpe": -0.25400700800304515,
    "best_profit_factor": 0.5811457630718967,
    "best_win_rate": 0.26666666666666666,
    "best_return": -5.545376123011183,
    "avg_sharpe": -0.5516620130415394
  }
}