{
  "asset": "TSLA",
  "strategy": "ADX_DI",
  "timestamp": "2026-03-06T00:41:47.918987",
  "best_params": {
    "period": 14,
    "adx_threshold": 25,
    "di_threshold": 30
  },
  "best_metric": "sharpe",
  "best_value": 0.27018688217655745,
  "total_combinations": 9,
  "valid_combinations": 9,
  "results_summary": {
    "best_sharpe": 0.27018688217655745,
    "best_profit_factor": 1.9285753549352898,
    "best_win_rate": 0.3709677419354839,
    "best_return": 22.5215200950921,
    "avg_sharpe": 0.10376352294003392
  }
}