{
  "asset": "V",
  "strategy": "ADX_DI",
  "timestamp": "2026-03-06T01:51:11.357590",
  "best_params": {
    "period": 14,
    "adx_threshold": 20,
    "di_threshold": 30
  },
  "best_metric": "sharpe",
  "best_value": -0.12972839794798055,
  "total_combinations": 9,
  "valid_combinations": 9,
  "results_summary": {
    "best_sharpe": -0.12972839794798055,
    "best_profit_factor": 0.6810254578859983,
    "best_win_rate": 0.22727272727272727,
    "best_return": -2.600990713539135,
    "avg_sharpe": -0.32423692791666064
  }
}