{
  "asset": "XRP-USD",
  "strategy": "Keltner_Breakout",
  "timestamp": "2026-03-05T22:51:32.026892",
  "best_params": {
    "ema_period": 10,
    "atr_period": 20,
    "atr_multiplier": 2.0,
    "confirmation_bars": 1
  },
  "best_metric": "sharpe",
  "best_value": 0.1911859613667677,
  "total_combinations": 36,
  "valid_combinations": 32,
  "results_summary": {
    "best_sharpe": 0.1911859613667677,
    "best_profit_factor": 2.1130405547478714,
    "best_win_rate": 0.6666666666666666,
    "best_return": 2.9478781691124163,
    "avg_sharpe": -12412487248.731949
  }
}