{
  "asset": "XRP-USD",
  "strategy": "Supply_Demand",
  "timestamp": "2026-03-05T22:52:56.436905",
  "best_params": {
    "zone_period": 10,
    "strength_bars": 3,
    "touch_tolerance": 0.005
  },
  "best_metric": "sharpe",
  "best_value": -0.6946959946925464,
  "total_combinations": 27,
  "valid_combinations": 5,
  "results_summary": {
    "best_sharpe": -0.6946959946925464,
    "best_profit_factor": 0.17534372545410024,
    "best_win_rate": 0.5,
    "best_return": -17.473383984558417,
    "avg_sharpe": -369546776660.4522
  }
}